forexflaggr/__init__.py
forexflaggr/src/dependencies.py
forexflaggr/src/forex_flaggr.py
forexflaggr/src/gam_model.py
forexflaggr/src/html_config.py
forexflaggr/src/loess_model.py
forexflaggr/src/pie_chart_recommendation.py
forexflaggr/src/stochastic_model_interface.py
forexflaggr-0.0.6.dist-info/LICENSE
forexflaggr-0.0.6.dist-info/METADATA
forexflaggr-0.0.6.dist-info/WHEEL
forexflaggr-0.0.6.dist-info/top_level.txt
forexflaggr-0.0.6.dist-info/RECORD
