Metadata-Version: 2.1
Name: forexflaggr
Version: 0.0.6
Summary: A minimal package to pull and analyse financial (exchange rate) data.
Home-page: https://github.com/ZachWolpe/forexflaggr
Author: Zach Wolpe
Author-email: zach.wolpe@mlxgo.com
License: MIT
Classifier: License :: OSI Approved :: MIT License
Classifier: Programming Language :: Python :: 3.10
Classifier: Operating System :: OS Independent
Requires-Python: >=3.8
License-File: LICENSE
Requires-Dist: plotly-express (>=0.4.1)
Requires-Dist: plotly (>=5.10.0)
Requires-Dist: yfinance (>=0.2.3)
Requires-Dist: pygam (>=0.8.0)
Requires-Dist: moepy (>=1.1.4)
Requires-Dist: setuptools (>=65.6.3)
Requires-Dist: kaleido (>=0.2.1)
Requires-Dist: nbformat
Provides-Extra: dev
Requires-Dist: pytest (>=7.0) ; extra == 'dev'
Requires-Dist: twine (>=4.0.2) ; extra == 'dev'
